cdmanalytics/__init__.py
cdmanalytics-0.0.2.dist-info/METADATA
cdmanalytics-0.0.2.dist-info/WHEEL
cdmanalytics-0.0.2.dist-info/top_level.txt
cdmanalytics-0.0.2.dist-info/RECORD
